<?xml version="1.0"?>
<ResourceWrapperCache xmlns:xsi="http://www.w3.org/2001/XMLSchema-instance" xmlns:xsd="http://www.w3.org/2001/XMLSchema">
  <entries>
    <Entry>
      <id>d34f5343-974f-4f08-be1f-e47059b94531</id>
      <resourcePath>itemimage.png</resourcePath>
      <resourceLastModified>2014-04-21T08:26:36+08:00</resourceLastModified>
      <resourceFileSize>50917</resourceFileSize>
      <extraXmlLastModified>2014-04-21T08:26:36+08:00</extraXmlLastModified>
      <extraXmlFileSize>2038</extraXmlFileSize>
    </Entry>
    <Entry>
      <id>32369fe1-9389-4ec8-ad2c-e21948321f56</id>
      <resourcePath>itemimage2.png</resourcePath>
      <resourceLastModified>2014-04-21T08:26:36+08:00</resourceLastModified>
      <resourceFileSize>31013</resourceFileSize>
      <extraXmlLastModified>2014-04-21T08:26:36+08:00</extraXmlLastModified>
      <extraXmlFileSize>2040</extraXmlFileSize>
    </Entry>
    <Entry>
      <id>e0359356-8b5a-4aab-a134-f5780408ef6f</id>
      <resourcePath>itemMask.png</resourcePath>
      <resourceLastModified>2014-04-21T08:26:36+08:00</resourceLastModified>
      <resourceFileSize>19415</resourceFileSize>
      <extraXmlLastModified>2014-04-21T08:26:36+08:00</extraXmlLastModified>
      <extraXmlFileSize>2036</extraXmlFileSize>
    </Entry>
    <Entry>
      <resourcePath>start.lua</resourcePath>
      <resourceLastModified>0001-01-01T00:00:00</resourceLastModified>
      <resourceFileSize>0</resourceFileSize>
      <extraXmlLastModified>0001-01-01T00:00:00</extraXmlLastModified>
      <extraXmlFileSize>0</extraXmlFileSize>
    </Entry>
    <Entry>
      <id>d33e3dcb-d881-4ecc-89e5-6d21c718548d</id>
      <resourcePath>textureBoat.xml</resourcePath>
      <resourceLastModified>2014-04-21T08:26:36+08:00</resourceLastModified>
      <resourceFileSize>2095</resourceFileSize>
      <extraXmlLastModified>0001-01-01T00:00:00</extraXmlLastModified>
      <extraXmlFileSize>0</extraXmlFileSize>
    </Entry>
    <Entry>
      <resourcePath>VariableItem.lua</resourcePath>
      <resourceLastModified>0001-01-01T00:00:00</resourceLastModified>
      <resourceFileSize>0</resourceFileSize>
      <extraXmlLastModified>0001-01-01T00:00:00</extraXmlLastModified>
      <extraXmlFileSize>0</extraXmlFileSize>
    </Entry>
  </entries>
</ResourceWrapperCache>